gymz/DefaultConfig.json
gymz/__init__.py
gymz/env_runner_thread.py
gymz/gym_wrapper.py
gymz/messages.py
gymz/misc.py
gymz/wrapper_base.py
gymz/zmq_command_receiver_thread.py
gymz/zmq_observation_sender_thread.py
gymz/zmq_reward_sender_thread.py
gymz-0.0.3.data/scripts/gymz-controller
gymz-0.0.3.dist-info/LICENSE
gymz-0.0.3.dist-info/METADATA
gymz-0.0.3.dist-info/WHEEL
gymz-0.0.3.dist-info/top_level.txt
gymz-0.0.3.dist-info/RECORD
